any_llm_client/__init__.py
any_llm_client/core.py
any_llm_client/http.py
any_llm_client/main.py
any_llm_client/py.typed
any_llm_client/retry.py
any_llm_client/clients/__init__.py
any_llm_client/clients/mock.py
any_llm_client/clients/openai.py
any_llm_client/clients/yandexgpt.py
any_llm_client-3.2.1.dist-info/METADATA
any_llm_client-3.2.1.dist-info/WHEEL
any_llm_client-3.2.1.dist-info/licenses/LICENSE
any_llm_client-3.2.1.dist-info/RECORD
